.DS_Store
offpath/.DS_Store
offpath/__init__.py
offpath/core.py
offpath/hooks/__init__.py
offpath/hooks/langchain.py
offpath/hooks/openai.py
offpath_minihook-0.1.0.dist-info/METADATA
offpath_minihook-0.1.0.dist-info/WHEEL
offpath_minihook-0.1.0.dist-info/top_level.txt
offpath_minihook-0.1.0.dist-info/RECORD
